Metadata-Version: 2.1
Name: drf-autoview
Version: 1.0.0
Summary: Django drf api generator
Home-page: https://github.com/sheoran/django-drf-autoview.git
Author: Deepak Sheoran
License: UNKNOWN
Platform: UNKNOWN
Classifier: Programming Language :: Python
Classifier: Programming Language :: Python :: 3
